__hyperlib_embedding.cpython-37m-i386-linux-gnu.so
hyperlib.libs/libstdc++-8baf04f9.so.6.0.28
hyperlib.libs/libgcc_s-8b50eaaa.so.1
hyperlib/__init__.py
hyperlib/embedding/__init__.py
hyperlib/embedding/metric.py
hyperlib/embedding/sarkar.py
hyperlib/embedding/treerep.py
hyperlib/utils/multiprecision.py
hyperlib/utils/__init__.py
hyperlib/utils/functional.py
hyperlib/utils/linalg.py
hyperlib/utils/graph.py
hyperlib/loss/__init__.py
hyperlib/loss/constrastive_loss.py
hyperlib/nn/__init__.py
hyperlib/nn/layers/__init__.py
hyperlib/nn/layers/lin_hyp.py
hyperlib/nn/layers/dense_attention.py
hyperlib/nn/optimizers/rsgd.py
hyperlib/nn/optimizers/__init__.py
hyperlib/manifold/base.py
hyperlib/manifold/__init__.py
hyperlib/manifold/lorentz.py
hyperlib/manifold/poincare.py
hyperlib/models/__init__.py
hyperlib/models/pehr.py
hyperlib-0.0.6.dist-info/WHEEL
hyperlib-0.0.6.dist-info/top_level.txt
hyperlib-0.0.6.dist-info/LICENSE
hyperlib-0.0.6.dist-info/METADATA
hyperlib-0.0.6.dist-info/RECORD
