Metadata-Version: 2.1
Name: hyperlib
Version: 0.0.6
Summary: Library that contains implementations of machine learning components in the hyperbolic space
Home-page: https://github.com/nalexai/hyperlib
Author: Nalex.ai
Author-email: info@nalexai.com
Project-URL: Source, https://github.com/nalexai/hyperlib
Project-URL: Issues, https://github.com/nalexai/hyperlib/issues
Classifier: Programming Language :: Python :: 3
Classifier: License :: OSI Approved :: MIT License
Classifier: Operating System :: OS Independent
Requires-Dist: numpy (>=1.19.3)
Requires-Dist: tensorflow (>=2.0.0)
Requires-Dist: scipy (>=1.7.0)
Requires-Dist: mpmath
Requires-Dist: networkx
Requires-Dist: pybind11 (>=2.7.0)
Requires-Dist: gmpy2
